lightfm_next.libs/libgomp-a34b3233.so.1.0.0
lightfm/evaluation.py
lightfm/_lightfm_fast_no_openmp.c
lightfm/cross_validation.py
lightfm/__init__.py
lightfm/version.py
lightfm/data.py
lightfm/_lightfm_fast_openmp.cpython-39-x86_64-linux-gnu.so
lightfm/lightfm.py
lightfm/_lightfm_fast_openmp.c
lightfm/_lightfm_fast.py
lightfm/datasets/movielens.py
lightfm/datasets/__init__.py
lightfm/datasets/stackexchange.py
lightfm/datasets/_common.py
lightfm_next-1.18.7.dist-info/METADATA
lightfm_next-1.18.7.dist-info/LICENSE
lightfm_next-1.18.7.dist-info/top_level.txt
lightfm_next-1.18.7.dist-info/WHEEL
lightfm_next-1.18.7.dist-info/RECORD
