Metadata-Version: 2.2
Name: lightfm-next
Version: 1.18.7
Summary: LightFM recommendation model - Python 3.12+ compatible fork
Author: midodimori (Forker)
Author-email: "Lyst Ltd (Maciej Kula)" <data@ly.st>
License: Apache-2.0
Project-URL: Homepage, https://github.com/midodimori/lightfm-next
Project-URL: Repository, https://github.com/midodimori/lightfm-next
Project-URL: Bug Tracker, https://github.com/midodimori/lightfm-next/issues
Project-URL: Original Project, https://github.com/lyst/lightfm
Project-URL: Original Documentation, http://lyst.github.io/lightfm/docs/home.html
Project-URL: Original Issues, https://github.com/lyst/lightfm/issues
Classifier: Development Status :: 5 - Production/Stable
Classifier: Topic :: Scientific/Engineering :: Artificial Intelligence
Classifier: Programming Language :: Python :: 3
Classifier: Programming Language :: Python :: 3.8
Classifier: Programming Language :: Python :: 3.9
Classifier: Programming Language :: Python :: 3.10
Classifier: Programming Language :: Python :: 3.11
Classifier: Programming Language :: Python :: 3.12
Requires-Python: >=3.8
License-File: LICENSE
Requires-Dist: numpy>=1.17.0
Requires-Dist: scipy>=1.0.0
Requires-Dist: requests
Requires-Dist: scikit-learn>=0.20.0
Provides-Extra: dev
Requires-Dist: pytest>=6.0; extra == "dev"
Requires-Dist: pytest-timeout; extra == "dev"
Requires-Dist: Cython>=3.0; extra == "dev"
Requires-Dist: setuptools<77.0.0,>=75.0.0; extra == "dev"
Requires-Dist: wheel; extra == "dev"
Requires-Dist: build; extra == "dev"
Requires-Dist: twine; extra == "dev"
Requires-Dist: bump2version; extra == "dev"
Provides-Extra: lint
Requires-Dist: flake8; extra == "lint"
Requires-Dist: black; extra == "lint"
Provides-Extra: docs
Requires-Dist: sphinx; extra == "docs"
Requires-Dist: sphinxcontrib-bibtex; extra == "docs"
Requires-Dist: sphinx_rtd_theme; extra == "docs"
